noaa_wildfires/__init__.py
noaa_wildfires/cli.py
noaa_wildfires-0.0.5.dist-info/LICENSE
noaa_wildfires-0.0.5.dist-info/METADATA
noaa_wildfires-0.0.5.dist-info/WHEEL
noaa_wildfires-0.0.5.dist-info/entry_points.txt
noaa_wildfires-0.0.5.dist-info/top_level.txt
noaa_wildfires-0.0.5.dist-info/RECORD
