Metadata-Version: 2.1
Name: noaa-wildfires
Version: 0.0.5
Summary: Download wildfires data from NOAA satellites
Home-page: https://palewi.re/docs/noaa-wildfires
Author: Ben Welsh
Author-email: b@palewi.re
License: MIT
Project-URL: Maintainer, https://github.com/datadesk
Project-URL: Source, https://github.com/datadesk/noaa-wildfires
Project-URL: Tracker, https://github.com/datadesk/noaa-wildfires/issues
Classifier: Development Status :: 5 - Production/Stable
Classifier: Programming Language :: Python
Classifier: Programming Language :: Python :: 3
Classifier: Programming Language :: Python :: 3.9
Classifier: Programming Language :: Python :: 3.10
Classifier: Programming Language :: Python :: 3.11
Classifier: License :: OSI Approved :: MIT License
License-File: LICENSE
Requires-Dist: fiona
Requires-Dist: geojson
Requires-Dist: click
Requires-Dist: requests
